llama_index/llms/openai_like/__init__.py
llama_index/llms/openai_like/base.py
flying_delta_llms_openai_like-0.1.0.dist-info/METADATA
flying_delta_llms_openai_like-0.1.0.dist-info/WHEEL
flying_delta_llms_openai_like-0.1.0.dist-info/RECORD
